kind_quasar/__init__.py
kind_quasar/calculator.py
kind_quasar/cli.py
kind_quasar-0.1.0.dist-info/METADATA
kind_quasar-0.1.0.dist-info/WHEEL
kind_quasar-0.1.0.dist-info/entry_points.txt
kind_quasar-0.1.0.dist-info/top_level.txt
kind_quasar-0.1.0.dist-info/RECORD
