Metadata-Version: 2.1
Name: kind-quasar
Version: 0.1.0
Summary: A simple package to calculate net profit and ROI.
Home-page: https://github.com/yourusername/finance_calculator
Author: Semyon Drozdov
Author-email: s.drozdov@edu.centraluniversity.ru
Classifier: Programming Language :: Python :: 3
Classifier: License :: OSI Approved :: MIT License
Classifier: Operating System :: OS Independent
